LICENSE
MANIFEST.in
README.md
setup.py
OASYS2_SHADOW4_Advanced.egg-info/PKG-INFO
OASYS2_SHADOW4_Advanced.egg-info/SOURCES.txt
OASYS2_SHADOW4_Advanced.egg-info/dependency_links.txt
OASYS2_SHADOW4_Advanced.egg-info/entry_points.txt
OASYS2_SHADOW4_Advanced.egg-info/not-zip-safe
OASYS2_SHADOW4_Advanced.egg-info/requires.txt
OASYS2_SHADOW4_Advanced.egg-info/top_level.txt
orangecontrib/__init__.py
orangecontrib/shadow4_advanced/__init__.py
orangecontrib/shadow4_advanced/menu/__init__.py
orangecontrib/shadow4_advanced/menu/ow_shadow4_advanced_menu.py
orangecontrib/shadow4_advanced/widgets/__init__.py
orangecontrib/shadow4_advanced/widgets/gui/__init__.py
orangecontrib/shadow4_advanced/widgets/gui/power_plot_xy.py
orangecontrib/shadow4_advanced/widgets/tools/__init__.py
orangecontrib/shadow4_advanced/widgets/tools/ow_fixed_rods_bender_mirror.py
orangecontrib/shadow4_advanced/widgets/tools/ow_flexural_hinge_bender_mirror.py
orangecontrib/shadow4_advanced/widgets/tools/ow_flux_calculator.py
orangecontrib/shadow4_advanced/widgets/tools/ow_footprint_file_reader.py
orangecontrib/shadow4_advanced/widgets/tools/ow_hybrid_fzp.py
orangecontrib/shadow4_advanced/widgets/tools/ow_hybrid_screen.py
orangecontrib/shadow4_advanced/widgets/tools/ow_hybrid_undulator.py
orangecontrib/shadow4_advanced/widgets/tools/ow_power_node_point.py
orangecontrib/shadow4_advanced/widgets/tools/ow_power_plot_xy.py
orangecontrib/shadow4_advanced/widgets/tools/ow_power_plot_xy_BM.py
orangecontrib/shadow4_advanced/widgets/tools/ow_simple_fzp.py
orangecontrib/shadow4_advanced/widgets/tools/ow_total_reflectivity.py
orangecontrib/shadow4_advanced/widgets/tools/icons/advanced.png
orangecontrib/shadow4_advanced/widgets/tools/icons/bm_plot_xy_power.png
orangecontrib/shadow4_advanced/widgets/tools/icons/cycle_power.png
orangecontrib/shadow4_advanced/widgets/tools/icons/fixed_rods_bender_mirror.png
orangecontrib/shadow4_advanced/widgets/tools/icons/fixed_rods_bender_scheme.png
orangecontrib/shadow4_advanced/widgets/tools/icons/flexural_hinge_bender_mirror.png
orangecontrib/shadow4_advanced/widgets/tools/icons/flexural_hinge_bender_scheme.png
orangecontrib/shadow4_advanced/widgets/tools/icons/flux.png
orangecontrib/shadow4_advanced/widgets/tools/icons/footprint_reader.png
orangecontrib/shadow4_advanced/widgets/tools/icons/hybrid_fzp.png
