Metadata-Version: 2.4
Name: OASYS2-SHADOW4-Advanced
Version: 0.0.20
Summary: oasys2-shadow4-advanced: Oasys 2 widgets for shadow4 - advanced tools
Home-page: https://github.com/oasys-kit/OASYS2-SHADOW4-Advanced
Download-URL: https://github.com/oasys-kit/OASYS2-SHADOW4-Advanced
Author: M. Sanchez del Rio, L. Rebuffi
Author-email: lrebuffi@anl.gov
License: MIT
Keywords: ray tracing,x-ray optics,oasys2
Classifier: Development Status :: 4 - Beta
Classifier: Environment :: X11 Applications :: Qt
Classifier: Environment :: Console
Classifier: Environment :: Plugins
Classifier: Programming Language :: Python
Classifier: Programming Language :: Python :: 3
Classifier: Intended Audience :: Science/Research
License-File: LICENSE
Requires-Dist: oasys2>=0.0.19
Requires-Dist: shadow4-advanced>=0.0.20
Requires-Dist: oasys2-shadow4>=0.0.18
Dynamic: author
Dynamic: author-email
Dynamic: classifier
Dynamic: description
Dynamic: download-url
Dynamic: home-page
Dynamic: keywords
Dynamic: license
Dynamic: license-file
Dynamic: requires-dist
Dynamic: summary
